Metadata-Version: 2.1
Name: odoo-addon-barcodes_generator_abstract
Version: 18.0.1.0.0.2
Requires-Python: >=3.10
Requires-Dist: odoo==18.0.*
Requires-Dist: python-barcode
Summary: Generate Barcodes for Any Models
Home-page: https://github.com/OCA/stock-logistics-barcode
License: AGPL-3
Author: GRAP, La Louve, LasLabs, Odoo Community Association (OCA)
Author-email: support@odoo-community.org
Classifier: Programming Language :: Python
Classifier: Framework :: Odoo
Classifier: Framework :: Odoo :: 18.0
Classifier: License :: OSI Approved :: GNU Affero General Public License v3
